{
  "protocolVersion": "spark.runtime.v1alpha1",
  "messageId": "msg_11111111111141111111111111111111",
  "type": "runtime.hello",
  "sentAt": "2026-05-21T00:00:01.000Z",
  "payload": {
    "runtimeId": "rt_11111111111141111111111111111111",
    "runtimeVersion": "0.1.0",
    "supportedFeatures": [
      "ws-control-v1",
      "multi-workspace-runtime-v1",
      "workspace-snapshot-v1",
      "workspace-clients-v1",
      "executor-client-v1",
      "snapshot-control-v1"
    ],
    "workspaceBindings": [
      {
        "bindingId": "rtwb_11111111111141111111111111111111",
        "localWorkspaceKey": "local-dev",
        "localPath": "/Users/test/workspaces/local-dev",
        "displayName": "Local development workspace",
        "status": "available",
        "capabilities": {},
        "diagnostics": {
          "platform": "darwin"
        },
        "connection": {
          "status": "connected",
          "lastSeenAt": "2026-05-21T00:00:01.000Z"
        },
        "borrowed": {
          "borrowed": true,
          "interactiveClientCount": 1,
          "borrowedByClientIds": ["wcl-tui-1"],
          "since": "2026-05-21T00:00:00.000Z"
        },
        "workspaceClients": [
          {
            "clientId": "wcl-tui-1",
            "kind": "interactive",
            "status": "connected",
            "displayName": "Spark TUI",
            "attachedAt": "2026-05-21T00:00:00.000Z",
            "lastSeenAt": "2026-05-21T00:00:01.000Z"
          }
        ],
        "executor": {
          "state": "online",
          "clientId": "exec-local-1",
          "activeInvocationCount": 0,
          "activeAgentCount": 0,
          "lastSeenAt": "2026-05-21T00:00:01.000Z"
        }
      }
    ]
  }
}
